README.md
setup.cfg
setup.py
hangmangame/__init__.py
hangmangame/__main__.py
hangmangame/hangmangame.py
hangmangame.egg-info/PKG-INFO
hangmangame.egg-info/SOURCES.txt
hangmangame.egg-info/dependency_links.txt
hangmangame.egg-info/requires.txt
hangmangame.egg-info/top_level.txt