Metadata-Version: 2.1
Name: hangmangame
Version: 0.0.1
Summary: Hangman game for terminal
Home-page: https://github.com/jeffrichardchemistry/hangmangame
Author: Jefferson Richard
Author-email: jrichardquimica@gmail.com
License: GNU General Public License v3.0
Keywords: Game terminal hangman
Platform: UNKNOWN
Classifier: Intended Audience :: End Users/Desktop
Classifier: License :: OSI Approved :: GNU General Public License v3 (GPLv3)
Classifier: Natural Language :: English
Classifier: Operating System :: POSIX :: Linux
Classifier: Operating System :: Microsoft :: Windows
Classifier: Operating System :: MacOS
Classifier: Programming Language :: Python
Classifier: Programming Language :: Python :: 3
